pyGenericPath/URL.py
pyGenericPath/__init__.py
pyGenericPath-0.2.1.dist-info/LICENSE.md
pyGenericPath-0.2.1.dist-info/METADATA
pyGenericPath-0.2.1.dist-info/WHEEL
pyGenericPath-0.2.1.dist-info/top_level.txt
pyGenericPath-0.2.1.dist-info/RECORD
