Metadata-Version: 2.1
Name: pyGenericPath
Version: 0.2.1
Summary: A generic path implementation to derive domain specific path libraries.
Home-page: https://github.com/Paebbels/pyGenericPath
Author: Patrick Lehmann
Author-email: Paebbels@gmail.com
License: UNKNOWN
Project-URL: Documentation, https://pyGenericPath.readthedocs.io/en/latest/
Project-URL: Source Code, https://github.com/Paebbels/pyGenericPath
Project-URL: Issue Tracker, https://github.com/Paebbels/pyGenericPath/issues
Keywords: Python3 Path Generic-Library
Platform: UNKNOWN
Classifier: License :: OSI Approved :: Apache Software License
Classifier: Operating System :: OS Independent
Classifier: Programming Language :: Python :: 3 :: Only
Classifier: Programming Language :: Python :: 3.6
Classifier: Programming Language :: Python :: 3.7
Classifier: Programming Language :: Python :: 3.8
Classifier: Programming Language :: Python :: 3.9
Classifier: Development Status :: 3 - Alpha
Classifier: Intended Audience :: Developers
Classifier: Topic :: Utilities
Requires-Python: >=3.6
Requires-Dist: py-flags (>=1.1.4)
Requires-Dist: pydecor (>=2.0.1)
